temod_forms/__init__.py
temod_forms/readers/__init__.py
temod_forms/readers/content.py
temod_forms/readers/dict_reader.py
temod_forms/readers/exceptions.py
temod_forms/readers/utils.py
temod_forms/renderers/html/__init__.py
temod_forms/renderers/html/base.py
temod_forms/renderers/html/entity.py
temod_forms/renderers/html/input.py
temod_forms/renderers/html/join.py
temod_forms/renderers/html/decorators/__init__.py
temod_forms/renderers/html/decorators/bootstrap.py
temod_forms-2.0.0.dist-info/LICENSE.txt
temod_forms-2.0.0.dist-info/METADATA
temod_forms-2.0.0.dist-info/WHEEL
temod_forms-2.0.0.dist-info/top_level.txt
temod_forms-2.0.0.dist-info/RECORD
